{"polverus":{"calculated":true,"class":"A","performance":789},"peyote":{"calculated":true,"class":"S+","performance":1151},"imperator3":{"calculated":true,"class":"A","performance":661},"molotok":{"calculated":true,"class":"S+","performance":17780},"bodhi2":{"calculated":true,"class":"S","performance":884},"baller6":{"calculated":true,"class":"S+","performance":1159},"ruiner4":{"calculated":true,"class":"S","performance":918},"hizoku":{"calculated":true,"class":"S+","performance":1678},"sentineldm":{"performance":1827,"class":"S+","calculated":true},"trophytruck":{"calculated":true,"class":"A","performance":789},"trash":{"calculated":true,"class":"S+","performance":1596},"gt500":{"calculated":true,"class":"S","performance":857},"impaler4":{"calculated":true,"class":"A","performance":755},"utillitruck2":{"calculated":true,"class":"S+","performance":1011},"sabregt":{"calculated":true,"class":"S","performance":951},"issi3":{"calculated":true,"class":"B","performance":588},"openwheel2":{"calculated":true,"class":"S+","performance":2085},"caracara2":{"calculated":true,"class":"S","performance":847},"emerus":{"calculated":true,"class":"S","performance":879},"hellion":{"calculated":true,"class":"S","performance":967},"z190wb":{"performance":1752,"class":"S+","calculated":true},"md902families":{"performance":896,"class":"S","calculated":true},"driftjester":{"calculated":true,"class":"A","performance":640},"alpha":{"calculated":true,"class":"S","performance":852},"double":{"calculated":true,"class":"S+","performance":1665},"vagner":{"calculated":true,"class":"S+","performance":1010},"pace_cypheranimvagos":{"performance":1881,"class":"S+","calculated":true},"buccaneer":{"calculated":true,"class":"S","performance":918},"windsor":{"calculated":true,"class":"S+","performance":1055},"vagrant":{"calculated":true,"class":"S","performance":835},"akuma":{"calculated":true,"class":"S+","performance":1589},"nero2":{"calculated":true,"class":"S+","performance":1415},"koryprordisciples":{"performance":1774,"class":"S+","calculated":true},"tampar":{"calculated":true,"class":"S+","performance":1393},"boxville3":{"performance":808,"class":"S","calculated":true},"police4":{"calculated":true,"class":"S+","performance":1413},"navarra":{"calculated":true,"class":"S+","performance":1151},"hexer":{"calculated":true,"class":"S+","performance":1283},"glendale2":{"calculated":true,"class":"A","performance":787},"polgauntlet":{"calculated":true,"class":"A","performance":723},"issi4":{"calculated":true,"class":"B","performance":551},"pace_cypheranimaod":{"performance":1881,"class":"S+","calculated":true},"kawaii":{"calculated":true,"class":"S+","performance":1157},"issi7":{"calculated":true,"class":"S","performance":998},"md902lostmc":{"performance":896,"class":"S","calculated":true},"policet3":{"calculated":true,"class":"S+","performance":1369},"pace_cypheranimballas":{"performance":1881,"class":"S+","calculated":true},"khanjali":{"calculated":true,"class":"B","performance":474},"stanier":{"calculated":true,"class":"S+","performance":1340},"vindicator":{"calculated":true,"class":"S+","performance":1860},"peyote3":{"calculated":true,"class":"S+","performance":1223},"pace_cypheranimlostmc":{"performance":1881,"class":"S+","calculated":true},"terbyte":{"calculated":true,"class":"B","performance":578},"bfinjection":{"calculated":true,"class":"S","performance":852},"pounder2":{"calculated":true,"class":"S+","performance":1080},"mule4":{"calculated":true,"class":"S","performance":808},"elytron":{"performance":1881,"class":"S+","calculated":true},"rubble":{"calculated":true,"class":"S","performance":808},"schlagenstr":{"performance":1881,"class":"S+","calculated":true},"cablecar":{"calculated":true,"class":"S+","performance":6552},"zhaba":{"calculated":true,"class":"A","performance":626},"boxville6":{"calculated":true,"class":"S","performance":808},"sanchez":{"calculated":true,"class":"S+","performance":1046},"tfremus":{"calculated":true,"class":"S+","performance":1738},"comet5":{"calculated":true,"class":"S","performance":819},"jugular":{"calculated":true,"class":"S+","performance":1054},"manchez":{"calculated":true,"class":"S+","performance":1504},"carbonrs":{"calculated":true,"class":"S+","performance":1472},"glendale":{"calculated":true,"class":"A","performance":787},"tropos":{"calculated":true,"class":"S+","performance":1157},"scramjet":{"calculated":true,"class":"A","performance":693},"gresley":{"calculated":true,"class":"S+","performance":1137},"tahoma":{"calculated":true,"class":"A","performance":755},"banshee2":{"calculated":true,"class":"A","performance":670},"romero":{"calculated":true,"class":"A","performance":765},"rebel":{"calculated":true,"class":"S+","performance":1137},"warrener2":{"calculated":true,"class":"A","performance":693},"deity":{"calculated":true,"class":"A","performance":787},"stratum":{"calculated":true,"class":"S+","performance":1361},"feltzer9":{"calculated":true,"class":"S+","performance":1678},"vivanite":{"calculated":true,"class":"S+","performance":1551},"amwbcometfamilies":{"performance":2267,"class":"S+","calculated":true},"paragon2":{"calculated":true,"class":"S+","performance":1022},"brigham":{"calculated":true,"class":"S","performance":808},"amwbcometvagos":{"performance":2267,"class":"S+","calculated":true},"dloader":{"calculated":true,"class":"B","performance":518},"tempesta2":{"performance":2841,"class":"S+","calculated":true},"kanjosj":{"calculated":true,"class":"A","performance":670},"lm87":{"calculated":true,"class":"S","performance":920},"turismor":{"calculated":true,"class":"S","performance":884},"kamswb":{"calculated":true,"class":"S","performance":879},"tyrant":{"calculated":true,"class":"S+","performance":1157},"ratel":{"calculated":true,"class":"B","performance":518},"cypherct":{"performance":1881,"class":"S+","calculated":true},"zr3802":{"calculated":true,"class":"S","performance":884},"supervolito":{"calculated":true,"class":"S","performance":896},"dominator7":{"calculated":true,"class":"S","performance":884},"italigtb":{"calculated":true,"class":"S+","performance":1415},"technical2":{"calculated":true,"class":"S","performance":884},"dlcinq":{"calculated":true,"class":"S+","performance":2733},"surfer3":{"calculated":true,"class":"D","performance":276},"chernobog":{"calculated":true,"class":"B","performance":554},"luxor2":{"calculated":true,"class":"S+","performance":2661},"cognoscenti":{"calculated":true,"class":"S","performance":964},"gurkharb":{"calculated":true,"class":"S","performance":967},"gstghell1":{"performance":1606,"class":"S+","calculated":true},"casco":{"calculated":true,"class":"S+","performance":1018},"pace_sunrisecartel":{"performance":1827,"class":"S+","calculated":true},"rapidgt2":{"calculated":true,"class":"S","performance":819},"tezeract":{"calculated":true,"class":"S+","performance":7310},"yosemite":{"calculated":true,"class":"A","performance":632},"swift":{"calculated":true,"class":"S","performance":830},"cheetah2":{"calculated":true,"class":"S+","performance":1087},"mower":{"calculated":true,"class":"D","performance":66},"impaler3":{"calculated":true,"class":"A","performance":755},"dlcomet6":{"calculated":true,"class":"S+","performance":2911},"stretch":{"calculated":true,"class":"S+","performance":1245},"fr36":{"calculated":true,"class":"S","performance":918},"youga3":{"calculated":true,"class":"S+","performance":1102},"insurgent2":{"calculated":true,"class":"B","performance":438},"executioner":{"calculated":true,"class":"A","performance":767},"xls":{"calculated":true,"class":"S+","performance":1137},"gburrito2":{"calculated":true,"class":"S+","performance":1296},"jubilee":{"calculated":true,"class":"S","performance":967},"rogue":{"calculated":true,"class":"S+","performance":17780},"kampfer":{"calculated":true,"class":"S+","performance":1536},"draugur":{"calculated":true,"class":"S","performance":847},"pace_sunriseballas":{"performance":1827,"class":"S+","calculated":true},"remuswb":{"performance":1827,"class":"S+","calculated":true},"hustler":{"calculated":true,"class":"A","performance":731},"miljet":{"calculated":true,"class":"S","performance":896},"cliffhanger":{"calculated":true,"class":"S+","performance":2150},"sugoi":{"calculated":true,"class":"S","performance":819},"saseverowb":{"performance":1902,"class":"S+","calculated":true},"md902disciples":{"performance":896,"class":"S","calculated":true},"oracle2":{"calculated":true,"class":"S","performance":986},"stromberg":{"calculated":true,"class":"S","performance":884},"blimp":{"performance":808,"class":"S","calculated":true},"bruiser2":{"calculated":true,"class":"B","performance":438},"pace_sunriseyakuza":{"performance":1827,"class":"S+","calculated":true},"monster5":{"calculated":true,"class":"B","performance":506},"elegyrh6":{"calculated":true,"class":"S+","performance":1881},"skylift":{"calculated":true,"class":"S","performance":808},"schafter2":{"calculated":true,"class":"S+","performance":1055},"taipan":{"calculated":true,"class":"S+","performance":1157},"f620d":{"calculated":true,"class":"S+","performance":1413},"cognoscenti2":{"calculated":true,"class":"S","performance":964},"vader":{"calculated":true,"class":"S+","performance":1277},"brickade2":{"calculated":true,"class":"A","performance":656},"howard":{"calculated":true,"class":"S+","performance":1318},"insurgent":{"calculated":true,"class":"B","performance":438},"blazer":{"calculated":true,"class":"S","performance":935},"dodo":{"calculated":true,"class":"S+","performance":1964},"brawler":{"calculated":true,"class":"S","performance":918},"dlissiamb":{"calculated":true,"class":"S+","performance":1849},"md902aztecas":{"performance":896,"class":"S","calculated":true},"jester2":{"calculated":true,"class":"S+","performance":1245},"faggio2":{"calculated":true,"class":"S","performance":947},"supervolito2":{"calculated":true,"class":"S","performance":896},"zombieb":{"calculated":true,"class":"S+","performance":1330},"rhinehart":{"calculated":true,"class":"S+","performance":1062},"yosemite6str":{"performance":1849,"class":"S+","calculated":true},"bifta":{"calculated":true,"class":"S","performance":918},"jester3":{"calculated":true,"class":"S","performance":852},"rt3000wb":{"performance":1827,"class":"S+","calculated":true},"eurosx32":{"calculated":true,"class":"A","performance":787},"issi8s":{"calculated":true,"class":"S+","performance":3723},"lazer":{"calculated":true,"class":"S+","performance":16715},"buffalowb":{"calculated":true,"class":"S+","performance":17002},"imperial":{"calculated":true,"class":"S+","performance":1795},"dubsta22":{"calculated":true,"class":"S+","performance":1752},"vd_tenfrally":{"performance":1881,"class":"S+","calculated":true},"dlmanch":{"calculated":true,"class":"S+","performance":2137},"growler":{"calculated":true,"class":"S","performance":884},"blazer4":{"calculated":true,"class":"S+","performance":1035},"riothuey":{"calculated":true,"class":"S","performance":830},"italigto":{"calculated":true,"class":"S+","performance":1126},"tornado2":{"calculated":true,"class":"S+","performance":1151},"blade":{"calculated":true,"class":"B","performance":573},"pounder":{"calculated":true,"class":"S+","performance":1102},"amwbcometyakuza":{"performance":2267,"class":"S+","calculated":true},"furia":{"calculated":true,"class":"S+","performance":1148},"ztype":{"calculated":true,"class":"S+","performance":1558},"tyrusgtr":{"performance":2110,"class":"S+","calculated":true},"pizzaboy":{"calculated":true,"class":"S","performance":875},"hakuchou2":{"calculated":true,"class":"S+","performance":1468},"pace_sunrisedisciples":{"performance":1827,"class":"S+","calculated":true},"dlshin":{"calculated":true,"class":"S+","performance":2143},"dubsta":{"calculated":true,"class":"S+","performance":1137},"utillitruck":{"calculated":true,"class":"S+","performance":1011},"dlcomni":{"calculated":true,"class":"S+","performance":2996},"gst10f1":{"performance":1881,"class":"S+","calculated":true},"nsandbrush4":{"calculated":true,"class":"S+","performance":1827},"diablous2":{"calculated":true,"class":"S+","performance":1562},"hachurac":{"calculated":true,"class":"S+","performance":1225},"everon2":{"calculated":true,"class":"S","performance":819},"gauntletc":{"calculated":true,"class":"S","performance":852},"furoregt":{"calculated":true,"class":"S","performance":951},"deveste":{"calculated":true,"class":"A","performance":787},"le7b":{"calculated":true,"class":"S","performance":920},"deathbike3":{"calculated":true,"class":"S+","performance":2228},"virgo":{"calculated":true,"class":"A","performance":639},"journey2":{"calculated":true,"class":"S","performance":808},"dominator2":{"calculated":true,"class":"S+","performance":1446},"jester4":{"calculated":true,"class":"S","performance":819},"pariah":{"calculated":true,"class":"S","performance":951},"jester3c":{"performance":2213,"class":"S+","calculated":true},"remus":{"calculated":true,"class":"A","performance":755},"hrd6":{"calculated":true,"class":"S+","performance":1126},"hermes":{"calculated":true,"class":"B","performance":573},"blazer3":{"calculated":true,"class":"S","performance":935},"dilettante2":{"calculated":true,"class":"A","performance":765},"novak":{"calculated":true,"class":"S+","performance":1225},"majimagt":{"calculated":true,"class":"S+","performance":1957},"driftsentinel":{"calculated":true,"class":"A","performance":732},"visione":{"calculated":true,"class":"S","performance":951},"sandking2":{"calculated":true,"class":"S+","performance":1137},"previon":{"calculated":true,"class":"S","performance":819},"burrito":{"calculated":true,"class":"S+","performance":1151},"vacca3":{"performance":1986,"class":"S+","calculated":true},"hrspec":{"calculated":true,"class":"S+","performance":1431},"wastelander":{"calculated":true,"class":"A","performance":656},"pace_sunriseaztecas":{"performance":1827,"class":"S+","calculated":true},"millennial":{"calculated":true,"class":"S","performance":852},"avenger2":{"calculated":true,"class":"S+","performance":1964},"barracks3":{"calculated":true,"class":"S+","performance":1596},"ruiner2":{"calculated":true,"class":"S","performance":884},"jb7002":{"calculated":true,"class":"S+","performance":1488},"halftrack":{"calculated":true,"class":"D","performance":76},"pd_heli":{"calculated":true,"class":"S+","performance":110021},"jet":{"calculated":true,"class":"S+","performance":2237},"club":{"calculated":true,"class":"S","performance":884},"sultan":{"calculated":true,"class":"S+","performance":1292},"tankercar":{"calculated":true,"class":"S+","performance":6552},"packer":{"calculated":true,"class":"B","performance":556},"tahoma2":{"calculated":true,"class":"S+","performance":1296},"ambuimp":{"calculated":true,"class":"S+","performance":1596},"surfer2":{"performance":276,"class":"D","calculated":true},"oppressor2":{"calculated":true,"class":"S+","performance":1447},"scheisser":{"calculated":true,"class":"S+","performance":1573},"conada":{"calculated":true,"class":"S","performance":918},"vanz23m2wb":{"performance":1957,"class":"S+","calculated":true},"cargoplane":{"performance":2237,"class":"S+","calculated":true},"blazer5":{"calculated":true,"class":"S+","performance":1035},"entity3":{"calculated":true,"class":"S+","performance":1157},"h4rxwindsorcus":{"performance":1752,"class":"S+","calculated":true},"drafter":{"calculated":true,"class":"S+","performance":1116},"strikeforce":{"calculated":true,"class":"S+","performance":16715},"vd_pamira":{"calculated":true,"class":"S","performance":951},"sultan2":{"calculated":true,"class":"S+","performance":1037},"gstzr3503":{"performance":1881,"class":"S+","calculated":true},"hotkniferod":{"performance":1672,"class":"S+","calculated":true},"koryproryakuza":{"performance":1774,"class":"S+","calculated":true},"trophytruck2":{"calculated":true,"class":"A","performance":789},"raiden":{"calculated":true,"class":"S","performance":967},"tornado3":{"calculated":true,"class":"S+","performance":1151},"emsscoutmk":{"calculated":true,"class":"S+","performance":1902},"draftgpr":{"performance":1881,"class":"S+","calculated":true},"utillitruck3":{"calculated":true,"class":"S+","performance":1011},"ripley":{"calculated":true,"class":"D","performance":155},"stalion":{"performance":787,"class":"A","calculated":true},"pace_sunriselostmc":{"performance":1827,"class":"S+","calculated":true},"velum":{"performance":2126,"class":"S+","calculated":true},"boor":{"calculated":true,"class":"S","performance":999},"valkyrie2":{"calculated":true,"class":"S","performance":830},"monster4":{"calculated":true,"class":"B","performance":506},"ninef2":{"calculated":true,"class":"S+","performance":1245},"shotaro":{"calculated":true,"class":"S+","performance":1667},"909_ch53":{"calculated":true,"class":"S","performance":808},"technical":{"calculated":true,"class":"S+","performance":1137},"jb700":{"calculated":true,"class":"S+","performance":1488},"castigator":{"calculated":true,"class":"S+","performance":1431},"jester":{"calculated":true,"class":"S+","performance":1245},"scdtm":{"performance":1827,"class":"S+","calculated":true},"contenderc":{"performance":1752,"class":"S+","calculated":true},"scorcher":{"calculated":true,"class":"S","performance":828},"dominator6":{"calculated":true,"class":"A","performance":693},"vulture":{"calculated":true,"class":"S","performance":852},"moonbeam2":{"calculated":true,"class":"S+","performance":1080},"surge":{"calculated":true,"class":"S","performance":830},"coquette5":{"calculated":true,"class":"S+","performance":1157},"seasparrow2":{"calculated":true,"class":"S","performance":922},"vigero3":{"calculated":true,"class":"A","performance":723},"annihilator":{"calculated":true,"class":"S","performance":808},"bjxl":{"calculated":true,"class":"S+","performance":1072},"zion3":{"calculated":true,"class":"A","performance":755},"baller7":{"calculated":true,"class":"S+","performance":1159},"bati901":{"calculated":true,"class":"S+","performance":1804},"feltold":{"calculated":true,"class":"S+","performance":1431},"faggio":{"calculated":true,"class":"S+","performance":1115},"dlballer8":{"calculated":true,"class":"S+","performance":2817},"hotknife":{"calculated":true,"class":"S","performance":835},"issi6":{"calculated":true,"class":"B","performance":551},"sultanrsv8":{"performance":1957,"class":"S+","calculated":true},"segway":{"calculated":true,"class":"C","performance":382},"sentinel":{"calculated":true,"class":"S+","performance":1488},"hachura":{"calculated":true,"class":"S+","performance":1225},"policeold1":{"calculated":true,"class":"S+","performance":1072},"elegyx":{"calculated":true,"class":"S+","performance":1752},"fugitive":{"calculated":true,"class":"S+","performance":1124},"tornado":{"calculated":true,"class":"S+","performance":1151},"freightcont2":{"calculated":true,"class":"S+","performance":6552},"dorado":{"calculated":true,"class":"S+","performance":1361},"taxi":{"calculated":true,"class":"S+","performance":1340},"rhino":{"calculated":true,"class":"B","performance":420},"vanillaschlagen":{"calculated":true,"class":"S","performance":884},"cheetah":{"calculated":true,"class":"S+","performance":1018},"locust":{"calculated":true,"class":"S","performance":944},"penumbra2":{"calculated":true,"class":"S+","performance":1062},"clique2":{"calculated":true,"class":"B","performance":460},"poldorado":{"calculated":true,"class":"S+","performance":1361},"chavosv6w":{"calculated":true,"class":"S+","performance":2448},"coquette2":{"calculated":true,"class":"S","performance":819},"rancherxl2":{"calculated":true,"class":"S+","performance":1072},"phantom4":{"calculated":true,"class":"B","performance":438},"mogul":{"calculated":true,"class":"S+","performance":2208},"tribike":{"calculated":true,"class":"S","performance":822},"pace_cypheranimaztecas":{"performance":1881,"class":"S+","calculated":true},"raiju":{"calculated":true,"class":"D","performance":113},"boorbc":{"performance":1733,"class":"S+","calculated":true},"veto2":{"calculated":true,"class":"C","performance":389},"coquette4c":{"performance":1979,"class":"S+","calculated":true},"hakuchou":{"calculated":true,"class":"S+","performance":1538},"mesa3":{"calculated":true,"class":"S+","performance":1137},"landstalker2":{"calculated":true,"class":"S+","performance":1203},"fcr":{"calculated":true,"class":"S+","performance":1467},"michelli":{"calculated":true,"class":"A","performance":793},"pace_cypheranimmafia":{"performance":1881,"class":"S+","calculated":true},"bulldozer":{"calculated":true,"class":"D","performance":328},"sc_dominatorwb":{"performance":1827,"class":"S+","calculated":true},"imorgon":{"calculated":true,"class":"A","performance":640},"ratloader":{"calculated":true,"class":"A","performance":661},"imperator":{"calculated":true,"class":"A","performance":661},"frogger2":{"calculated":true,"class":"S","performance":830},"Hoonie":{"performance":1431,"class":"S+","calculated":true},"dlamb":{"calculated":true,"class":"S+","performance":1596},"deviant":{"calculated":true,"class":"A","performance":661},"tula":{"calculated":true,"class":"S+","performance":1964},"tampa3":{"calculated":true,"class":"S","performance":999},"tractor3":{"calculated":true,"class":"D","performance":22},"dominator":{"calculated":true,"class":"S+","performance":1413},"amwbcometballas":{"performance":2267,"class":"S+","calculated":true},"burrito2":{"calculated":true,"class":"S+","performance":1151},"journey":{"calculated":true,"class":"S","performance":808},"gp1wb":{"performance":2267,"class":"S+","calculated":true},"uniobepdb":{"performance":1957,"class":"S+","calculated":true},"daemon2":{"calculated":true,"class":"S+","performance":1268},"amwbcometmafia":{"performance":2267,"class":"S+","calculated":true},"mesa":{"calculated":true,"class":"S+","performance":1137},"scarab":{"calculated":true,"class":"S","performance":825},"recursion":{"calculated":true,"class":"S+","performance":1720},"toreador":{"calculated":true,"class":"S","performance":852},"vigerozxwbc":{"performance":2033,"class":"S+","calculated":true},"gauntlet4":{"calculated":true,"class":"A","performance":723},"chimera":{"calculated":true,"class":"A","performance":608},"mesaxl":{"calculated":true,"class":"S+","performance":1848},"felon2":{"calculated":true,"class":"S","performance":986},"gp1":{"calculated":true,"class":"S","performance":879},"dlstalker2":{"calculated":true,"class":"S+","performance":2132},"slamvan4":{"calculated":true,"class":"A","performance":610},"dlwheelchair":{"calculated":true,"class":"B","performance":473},"pfister811":{"calculated":true,"class":"S+","performance":1379},"bansheeas":{"performance":2033,"class":"S+","calculated":true},"massacro2":{"calculated":true,"class":"S","performance":819},"baller4":{"calculated":true,"class":"S+","performance":1159},"sentinel_rts":{"performance":1903,"class":"S+","calculated":true},"cinquemila":{"calculated":true,"class":"A","performance":723},"elegant":{"calculated":true,"class":"S","performance":918},"freecrawler":{"calculated":true,"class":"S","performance":847},"buffaloh":{"calculated":true,"class":"S+","performance":1227},"faction3":{"calculated":true,"class":"A","performance":723},"driftremus":{"calculated":true,"class":"A","performance":732},"powersurge":{"calculated":true,"class":"S+","performance":2276},"pace_cypheranimcartel":{"performance":1881,"class":"S+","calculated":true},"tampa2":{"performance":1037,"class":"S+","calculated":true},"zentorno":{"calculated":true,"class":"S+","performance":1180},"rhinetaxi":{"calculated":true,"class":"S+","performance":1062},"hotring":{"calculated":true,"class":"S","performance":819},"dlpanto":{"calculated":true,"class":"S+","performance":1694},"dominator5":{"calculated":true,"class":"A","performance":693},"comet2":{"calculated":true,"class":"S","performance":884},"vayra":{"calculated":true,"class":"S+","performance":1349},"freight":{"calculated":true,"class":"S+","performance":6552},"schafter4":{"calculated":true,"class":"S","performance":986},"bobcatxl":{"calculated":true,"class":"A","performance":765},"cwagon":{"calculated":true,"class":"S","performance":986},"docktug":{"calculated":true,"class":"D","performance":113},"brutus2":{"calculated":true,"class":"S+","performance":1008},"tailgater":{"calculated":true,"class":"S","performance":986},"akula":{"calculated":true,"class":"S","performance":808},"schlagen":{"calculated":true,"class":"S","performance":884},"tyrus":{"calculated":true,"class":"S","performance":920},"radi":{"calculated":true,"class":"S+","performance":1270},"cypher":{"calculated":true,"class":"A","performance":693},"drifteuros":{"calculated":true,"class":"A","performance":684},"policeb":{"calculated":true,"class":"S+","performance":1283},"brioso2":{"calculated":true,"class":"B","performance":573},"buzzard":{"calculated":true,"class":"S","performance":830},"koryproraod":{"performance":1774,"class":"S+","calculated":true},"sentinelsg4":{"calculated":true,"class":"S","performance":884},"calico":{"calculated":true,"class":"S+","performance":1126},"boorc":{"calculated":true,"class":"S+","performance":1163},"tornado4":{"calculated":true,"class":"S+","performance":1151},"vortex":{"calculated":true,"class":"S+","performance":1761},"boxville2":{"calculated":true,"class":"S","performance":808},"amwbcometlostmc":{"performance":2267,"class":"S+","calculated":true},"SCSugoi":{"performance":1881,"class":"S+","calculated":true},"zr350":{"calculated":true,"class":"S","performance":819},"openwheel1":{"calculated":true,"class":"S+","performance":1928},"youga2":{"calculated":true,"class":"S+","performance":1080},"emperor3":{"calculated":true,"class":"S+","performance":1080},"airtug":{"calculated":true,"class":"D","performance":44},"menacer":{"calculated":true,"class":"A","performance":767},"ingot":{"calculated":true,"class":"S","performance":918},"primo2":{"calculated":true,"class":"S","performance":918},"daemon":{"calculated":true,"class":"S+","performance":1268},"besra":{"calculated":true,"class":"S+","performance":17780},"faction2":{"calculated":true,"class":"S","performance":951},"landstalker":{"calculated":true,"class":"S+","performance":1203},"starling":{"calculated":true,"class":"S+","performance":6681},"hydra":{"calculated":true,"class":"D","performance":200},"tribike3":{"calculated":true,"class":"S","performance":822},"scrap":{"calculated":true,"class":"S","performance":874},"baller5":{"calculated":true,"class":"S+","performance":1159},"speedo4":{"calculated":true,"class":"S+","performance":1151},"kanjo":{"calculated":true,"class":"A","performance":632},"glendalelimo":{"calculated":true,"class":"S","performance":852},"vetir":{"calculated":true,"class":"B","performance":404},"amwbcomettriads":{"performance":2267,"class":"S+","calculated":true},"rapidgt3":{"calculated":true,"class":"S","performance":852},"reever":{"calculated":true,"class":"S+","performance":1680},"sentinel3":{"calculated":true,"class":"S","performance":884},"comet4":{"calculated":true,"class":"S+","performance":1257},"sadler2":{"calculated":true,"class":"S+","performance":1072},"manchez3":{"calculated":true,"class":"S+","performance":1369},"dukes2":{"calculated":true,"class":"A","performance":639},"jackal":{"calculated":true,"class":"S+","performance":1413},"firetruk":{"calculated":true,"class":"S+","performance":1542},"tulip2":{"calculated":true,"class":"A","performance":755},"domttc":{"performance":6123,"class":"S+","calculated":true},"tribike2":{"calculated":true,"class":"S","performance":822},"zr3803":{"calculated":true,"class":"S","performance":884},"cyclone":{"calculated":true,"class":"S+","performance":1030},"chino2":{"calculated":true,"class":"A","performance":639},"iwagen":{"calculated":true,"class":"A","performance":656},"gauntlet5":{"calculated":true,"class":"S+","performance":1055},"bus":{"calculated":true,"class":"A","performance":767},"tractor4":{"performance":483,"class":"B","calculated":true},"seminole":{"calculated":true,"class":"S+","performance":1203},"faction":{"calculated":true,"class":"S","performance":951},"scarab3":{"calculated":true,"class":"S","performance":825},"accolade":{"calculated":true,"class":"S+","performance":1225},"savestrare":{"calculated":true,"class":"S+","performance":1646},"lynx":{"calculated":true,"class":"S","performance":986},"caddy3":{"calculated":true,"class":"D","performance":222},"sultan3":{"calculated":true,"class":"S","performance":999},"eva":{"calculated":true,"class":"D","performance":247},"driftcypher":{"calculated":true,"class":"A","performance":640},"mixer2":{"calculated":true,"class":"S+","performance":1596},"sovereign":{"calculated":true,"class":"S+","performance":1283},"reaper":{"calculated":true,"class":"S","performance":819},"slamtruck":{"calculated":true,"class":"B","performance":578},"freightcont1":{"calculated":true,"class":"S+","performance":6552},"reagpr":{"performance":2267,"class":"S+","calculated":true},"kuruma":{"calculated":true,"class":"S+","performance":1126},"cog552":{"calculated":true,"class":"S","performance":964},"tigon":{"calculated":true,"class":"S","performance":922},"blazer2":{"calculated":true,"class":"S","performance":811},"fireengb":{"calculated":true,"class":"S+","performance":1542},"driftfr36":{"calculated":true,"class":"A","performance":640},"tenf":{"calculated":true,"class":"S","performance":819},"dune5":{"calculated":true,"class":"S","performance":944},"virgo2":{"calculated":true,"class":"A","performance":639},"forklift":{"calculated":true,"class":"D","performance":54},"limo2":{"calculated":true,"class":"B","performance":460},"outlaw":{"calculated":true,"class":"B","performance":598},"swinger":{"calculated":true,"class":"A","performance":794},"hauler":{"calculated":true,"class":"C","performance":382},"italigts":{"performance":1126,"class":"S+","calculated":true},"asea2":{"calculated":true,"class":"S","performance":986},"emperor":{"calculated":true,"class":"S+","performance":1080},"infernus2":{"calculated":true,"class":"S","performance":819},"blista":{"calculated":true,"class":"S","performance":852},"koryprorfamilies":{"performance":1774,"class":"S+","calculated":true},"stunt":{"calculated":true,"class":"S+","performance":2259},"phoenix":{"calculated":true,"class":"S","performance":986},"Prisonvan3rb":{"calculated":true,"class":"S+","performance":1369},"formula":{"calculated":true,"class":"S+","performance":1621},"barrage":{"calculated":true,"class":"S+","performance":1072},"mule":{"calculated":true,"class":"S","performance":808},"mesa2":{"calculated":true,"class":"S+","performance":1137},"cavalcade3":{"calculated":true,"class":"S+","performance":1008},"maverick":{"calculated":true,"class":"S","performance":830},"dominator3":{"calculated":true,"class":"A","performance":693},"flivver":{"calculated":true,"class":"D","performance":155},"slamvan5":{"calculated":true,"class":"A","performance":610},"ardent":{"calculated":true,"class":"S+","performance":1018},"jestgpr":{"performance":1957,"class":"S+","calculated":true},"tempestaes":{"performance":2591,"class":"S+","calculated":true},"slamvan2":{"calculated":true,"class":"A","performance":661},"gstarg2":{"performance":1957,"class":"S+","calculated":true},"pcj":{"calculated":true,"class":"S+","performance":1043},"nebula":{"calculated":true,"class":"B","performance":600},"mule2":{"calculated":true,"class":"S","performance":808},"titan":{"calculated":true,"class":"S+","performance":2237},"lectro":{"calculated":true,"class":"S+","performance":1277},"cerberus2":{"calculated":true,"class":"A","performance":743},"conada2":{"calculated":true,"class":"S","performance":918},"pyro":{"calculated":true,"class":"S+","performance":17780},"turismo2lm":{"performance":2428,"class":"S+","calculated":true},"clique":{"calculated":true,"class":"S","performance":819},"picador":{"calculated":true,"class":"S+","performance":1159},"thrust":{"calculated":true,"class":"S+","performance":1786},"aleutian":{"calculated":true,"class":"S+","performance":1431},"thrax":{"calculated":true,"class":"S+","performance":1279},"phantom":{"calculated":true,"class":"B","performance":438},"vestra":{"calculated":true,"class":"S","performance":874},"cheburek":{"calculated":true,"class":"S","performance":884},"jesterx":{"calculated":true,"class":"S+","performance":1245},"police3":{"calculated":true,"class":"S","performance":951},"seasparrow":{"calculated":true,"class":"S","performance":830},"insurgent3":{"calculated":true,"class":"A","performance":767},"voodoo":{"calculated":true,"class":"S+","performance":1151},"pace_sunrisetriads":{"performance":1827,"class":"S+","calculated":true},"khamelion":{"calculated":true,"class":"S","performance":896},"torero2":{"calculated":true,"class":"S+","performance":1245},"policegcrb":{"calculated":true,"class":"A","performance":736},"r300":{"calculated":true,"class":"S","performance":819},"dominator10":{"calculated":true,"class":"S+","performance":1087},"baller3":{"calculated":true,"class":"S+","performance":1159},"contender":{"calculated":true,"class":"S","performance":945},"poldominator10":{"calculated":true,"class":"S+","performance":1087},"turismocs":{"calculated":true,"class":"S+","performance":1227},"impaler5":{"calculated":true,"class":"S+","performance":1195},"koryprorlostmc":{"performance":1774,"class":"S+","calculated":true},"felon":{"calculated":true,"class":"S+","performance":1195},"hycrh7":{"performance":1979,"class":"S+","calculated":true},"nsandbrush6":{"calculated":true,"class":"S+","performance":1827},"rocoto":{"calculated":true,"class":"S+","performance":1624},"seraph3":{"calculated":true,"class":"S","performance":986},"l35l":{"calculated":true,"class":"S","performance":967},"eudora":{"calculated":true,"class":"S+","performance":1151},"rrocket":{"calculated":true,"class":"B","performance":442},"exemplar":{"calculated":true,"class":"S+","performance":1195},"windsor2":{"calculated":true,"class":"S+","performance":1033},"xls2":{"calculated":true,"class":"S+","performance":1137},"paragon3":{"calculated":true,"class":"S+","performance":1094},"toros":{"calculated":true,"class":"S+","performance":1225},"tourbus":{"calculated":true,"class":"B","performance":496},"coquette":{"calculated":true,"class":"S","performance":951},"sunrise1":{"performance":1957,"class":"S+","calculated":true},"oraclelwb":{"calculated":true,"class":"S+","performance":1267},"youga4":{"calculated":true,"class":"S+","performance":1151},"sentinel2":{"calculated":true,"class":"S+","performance":1488},"mk2vigerozx":{"performance":1957,"class":"S+","calculated":true},"kamacho":{"calculated":true,"class":"S","performance":967},"policet":{"calculated":true,"class":"S+","performance":1151},"t20":{"calculated":true,"class":"S+","performance":1180},"slamvan":{"calculated":true,"class":"A","performance":693},"benson":{"calculated":true,"class":"S+","performance":1480},"shamal":{"calculated":true,"class":"S+","performance":2661},"prototipo":{"calculated":true,"class":"S+","performance":1413},"dune":{"calculated":true,"class":"B","performance":600},"tailgater2":{"calculated":true,"class":"S+","performance":1018},"cargobob":{"calculated":true,"class":"S","performance":808},"md902ballas":{"performance":896,"class":"S","calculated":true},"sagauntletstreet":{"performance":1957,"class":"S+","calculated":true},"entityxf":{"calculated":true,"class":"S+","performance":1325},"strage":{"calculated":true,"class":"S+","performance":1213},"serena":{"calculated":true,"class":"S+","performance":1087},"nokota":{"calculated":true,"class":"S+","performance":17780},"futo":{"calculated":true,"class":"S+","performance":1194},"paragon":{"calculated":true,"class":"S+","performance":1022},"polbike":{"calculated":true,"class":"S+","performance":1378},"domgtcoupe":{"calculated":true,"class":"S","performance":986},"imperator2":{"calculated":true,"class":"A","performance":661},"mule3":{"calculated":true,"class":"B","performance":438},"dubsta3":{"calculated":true,"class":"A","performance":767},"blis2gpr":{"calculated":true,"class":"A","performance":750},"polsentinel":{"calculated":true,"class":"S+","performance":5461},"ruffian":{"calculated":true,"class":"S+","performance":1336},"speedo":{"calculated":true,"class":"S+","performance":1151},"swift2":{"calculated":true,"class":"S","performance":830},"sadler":{"calculated":true,"class":"S+","performance":1072},"apc":{"calculated":true,"class":"B","performance":420},"l35":{"calculated":true,"class":"S","performance":967},"futo2":{"calculated":true,"class":"S","performance":857},"nightblade":{"calculated":true,"class":"S+","performance":1498},"playboy":{"performance":1372,"class":"S+","calculated":true},"corsita":{"calculated":true,"class":"S","performance":819},"schwarzer2":{"performance":1881,"class":"S+","calculated":true},"btype3":{"calculated":true,"class":"B","performance":600},"gstnio2":{"performance":1957,"class":"S+","calculated":true},"brioso":{"calculated":true,"class":"S","performance":917},"crusader":{"calculated":true,"class":"S+","performance":1137},"elegyw":{"calculated":true,"class":"S+","performance":1733},"clubgtr":{"calculated":true,"class":"S+","performance":1195},"blista2":{"calculated":true,"class":"S","performance":884},"xa21":{"calculated":true,"class":"S+","performance":1180},"luxor":{"calculated":true,"class":"S+","performance":2661},"amwbcometdisciples":{"performance":2267,"class":"S+","calculated":true},"dlcade3":{"calculated":true,"class":"S+","performance":2733},"manana2":{"calculated":true,"class":"S","performance":986},"formula2":{"calculated":true,"class":"S+","performance":1773},"premier":{"calculated":true,"class":"S","performance":986},"cerberus":{"calculated":true,"class":"A","performance":743},"trash2":{"calculated":true,"class":"S+","performance":1596},"vigero2":{"calculated":true,"class":"A","performance":755},"rancherxl":{"calculated":true,"class":"S+","performance":1072},"peyote2":{"calculated":true,"class":"A","performance":661},"stingergt":{"calculated":true,"class":"S+","performance":1018},"vigero":{"calculated":true,"class":"S","performance":918},"driftfuto":{"calculated":true,"class":"A","performance":782},"pace_cypheranimdisciples":{"performance":1881,"class":"S+","calculated":true},"omnisegt":{"calculated":true,"class":"A","performance":713},"jesterwb":{"performance":4180,"class":"S+","calculated":true},"swatcarrier":{"calculated":true,"class":"S+","performance":1827},"revolter":{"calculated":true,"class":"S","performance":847},"bati2":{"calculated":true,"class":"S+","performance":1672},"cargobob3":{"calculated":true,"class":"S","performance":808},"caracara":{"calculated":true,"class":"A","performance":767},"zr390":{"calculated":true,"class":"S+","performance":1678},"pipistrello":{"calculated":true,"class":"S+","performance":1030},"ninef":{"calculated":true,"class":"S+","performance":1245},"fmj":{"calculated":true,"class":"S","performance":951},"kalahari":{"calculated":true,"class":"A","performance":770},"monster3":{"calculated":true,"class":"B","performance":506},"buffalo4":{"calculated":true,"class":"A","performance":787},"gresleyh":{"calculated":true,"class":"S+","performance":1292},"volatus":{"calculated":true,"class":"S","performance":896},"turismorr":{"performance":2841,"class":"S+","calculated":true},"dune2":{"calculated":true,"class":"B","performance":600},"pigalle":{"calculated":true,"class":"S+","performance":1488},"phantom3":{"calculated":true,"class":"B","performance":438},"ellie":{"calculated":true,"class":"A","performance":693},"bf400":{"calculated":true,"class":"S+","performance":1809},"koryprortriads":{"performance":1774,"class":"S+","calculated":true},"brutus":{"calculated":true,"class":"S+","performance":1008},"zombiea":{"calculated":true,"class":"S+","performance":1330},"turismo2":{"calculated":true,"class":"S","performance":922},"stafford":{"calculated":true,"class":"A","performance":679},"weevil":{"calculated":true,"class":"A","performance":610},"gb200":{"calculated":true,"class":"S","performance":999},"vectre":{"calculated":true,"class":"S","performance":906},"koryproraztecas":{"performance":1774,"class":"S+","calculated":true},"shinobi":{"calculated":true,"class":"S+","performance":2144},"faggio3":{"calculated":true,"class":"S+","performance":1258},"penumbra":{"calculated":true,"class":"S","performance":918},"mixer":{"performance":1596,"class":"S+","calculated":true},"deathbike":{"calculated":true,"class":"S+","performance":2228},"bagger":{"calculated":true,"class":"S+","performance":1170},"t20gtr":{"performance":2347,"class":"S+","calculated":true},"ignus":{"calculated":true,"class":"S+","performance":1245},"boxville4":{"calculated":true,"class":"S","performance":808},"m420":{"calculated":true,"class":"S+","performance":1520},"warrener":{"calculated":true,"class":"B","performance":600},"driftvorschlag":{"calculated":true,"class":"A","performance":684},"cavalcade":{"calculated":true,"class":"S+","performance":1072},"avenger":{"calculated":true,"class":"S+","performance":1964},"scarab2":{"calculated":true,"class":"S","performance":825},"baller2":{"calculated":true,"class":"S+","performance":1159},"panthere":{"calculated":true,"class":"S","performance":922},"tiptruck":{"calculated":true,"class":"S","performance":808},"champion":{"calculated":true,"class":"S","performance":951},"neon":{"calculated":true,"class":"S+","performance":1030},"patriot":{"calculated":true,"class":"S+","performance":1137},"virtue":{"calculated":true,"class":"S","performance":999},"tampa":{"calculated":true,"class":"A","performance":755},"hycsun":{"performance":1827,"class":"S+","calculated":true},"dlemsb":{"calculated":true,"class":"S+","performance":1786},"sancyb4":{"calculated":true,"class":"S+","performance":2045},"comet7":{"calculated":true,"class":"S","performance":884},"speedo5":{"calculated":true,"class":"S+","performance":1151},"blimp3":{"calculated":true,"class":"S","performance":808},"hrgt6r":{"performance":1881,"class":"S+","calculated":true},"sddriftvet":{"performance":1431,"class":"S+","calculated":true},"tempesta":{"calculated":true,"class":"S+","performance":1116},"coureur":{"calculated":true,"class":"A","performance":632},"amwbcometcartel":{"performance":2267,"class":"S+","calculated":true},"vstr":{"calculated":true,"class":"A","performance":693},"tulip2s":{"calculated":true,"class":"S+","performance":1361},"pace_sunrisevagos":{"performance":1827,"class":"S+","calculated":true},"komodafr":{"performance":1806,"class":"S+","calculated":true},"mamba":{"calculated":true,"class":"S","performance":819},"roxanne":{"calculated":true,"class":"S+","performance":1700},"pony2":{"calculated":true,"class":"S+","performance":1151},"elegyheritage":{"calculated":true,"class":"S+","performance":1431},"gauntlet6":{"calculated":true,"class":"A","performance":723},"feltzer3":{"calculated":true,"class":"A","performance":755},"intruder":{"calculated":true,"class":"S+","performance":1055},"gargoyle":{"calculated":true,"class":"S+","performance":2228},"s80":{"calculated":true,"class":"S","performance":920},"polgreenwood":{"calculated":true,"class":"S+","performance":1318},"panto":{"calculated":true,"class":"A","performance":670},"emperor2":{"calculated":true,"class":"S+","performance":1080},"cog55":{"calculated":true,"class":"S","performance":986},"gstjc2":{"performance":1672,"class":"S+","calculated":true},"amwbcometaztecas":{"performance":2267,"class":"S+","calculated":true},"dynasty":{"calculated":true,"class":"A","performance":701},"squaddie":{"calculated":true,"class":"S+","performance":1137},"md902cartel":{"performance":896,"class":"S","calculated":true},"md902triads":{"performance":896,"class":"S","calculated":true},"sabregt2":{"calculated":true,"class":"S","performance":951},"euros":{"calculated":true,"class":"S","performance":852},"granger2":{"calculated":true,"class":"S","performance":884},"rrseminalhawkxz":{"calculated":true,"class":"S+","performance":2825},"buzzard2":{"calculated":true,"class":"S","performance":830},"huntley":{"calculated":true,"class":"S+","performance":1225},"vacca2":{"performance":1957,"class":"S+","calculated":true},"blimp2":{"performance":808,"class":"S","calculated":true},"bati":{"calculated":true,"class":"S+","performance":1672},"massacro":{"calculated":true,"class":"S","performance":819},"clubta":{"performance":1372,"class":"S+","calculated":true},"amwbcometaod":{"performance":2267,"class":"S+","calculated":true},"mh6":{"calculated":true,"class":"S+","performance":16157},"ziongtc":{"performance":2289,"class":"S+","calculated":true},"zentornoc":{"performance":1957,"class":"S+","calculated":true},"italigtoc":{"performance":2347,"class":"S+","calculated":true},"r300w":{"performance":1957,"class":"S+","calculated":true},"koryprormafia":{"performance":1774,"class":"S+","calculated":true},"pace_cypheranimyakuza":{"performance":1881,"class":"S+","calculated":true},"surano":{"calculated":true,"class":"S","performance":951},"pace_sunriseaod":{"performance":1827,"class":"S+","calculated":true},"granger":{"calculated":true,"class":"S+","performance":1137},"voodoo2":{"calculated":true,"class":"S+","performance":1151},"vertice":{"performance":1986,"class":"S+","calculated":true},"torero":{"calculated":true,"class":"S","performance":951},"pace_cypheranimtriads":{"performance":1881,"class":"S+","calculated":true},"pace_sunrisemafia":{"performance":1827,"class":"S+","calculated":true},"koryprorballas":{"performance":1774,"class":"S+","calculated":true},"pace_sunrisefamilies":{"performance":1827,"class":"S+","calculated":true},"rapidgte":{"performance":1881,"class":"S+","calculated":true},"koryprorvagos":{"performance":1774,"class":"S+","calculated":true},"slamvan6":{"calculated":true,"class":"A","performance":610},"cargoplane2":{"calculated":true,"class":"S+","performance":2237},"police5":{"calculated":true,"class":"S+","performance":1413},"italirsx":{"calculated":true,"class":"S+","performance":1126},"zentorno2":{"performance":2267,"class":"S+","calculated":true},"towtruck":{"calculated":true,"class":"S","performance":874},"dlballer7":{"calculated":true,"class":"S+","performance":2743},"cargobob4":{"calculated":true,"class":"S","performance":808},"italigtb2":{"calculated":true,"class":"S+","performance":1448},"md902mafia":{"performance":896,"class":"S","calculated":true},"seven70":{"calculated":true,"class":"S+","performance":1018},"defiler":{"calculated":true,"class":"S+","performance":1690},"md902yakuza":{"performance":896,"class":"S","calculated":true},"pranger":{"calculated":true,"class":"S+","performance":1072},"burrito3":{"calculated":true,"class":"S+","performance":1151},"pbus":{"calculated":true,"class":"C","performance":382},"rapidgt":{"calculated":true,"class":"S","performance":819},"gauntlet3":{"calculated":true,"class":"A","performance":755},"audace":{"performance":2465,"class":"S+","calculated":true},"cerberus3":{"calculated":true,"class":"A","performance":743},"sc1":{"calculated":true,"class":"S","performance":951},"weevil2":{"calculated":true,"class":"S+","performance":1030},"police":{"calculated":true,"class":"S+","performance":1413},"ruiner3":{"calculated":true,"class":"S+","performance":1446},"rcbandito":{"calculated":true,"class":"S+","performance":1436},"mraprb":{"calculated":true,"class":"A","performance":767},"annihilator2":{"calculated":true,"class":"S","performance":808},"zion":{"calculated":true,"class":"S+","performance":1564},"tenf2":{"calculated":true,"class":"S","performance":819},"yosemiteswb":{"calculated":true,"class":"S+","performance":1292},"asteropers":{"calculated":true,"class":"S","performance":852},"mammatus":{"calculated":true,"class":"S+","performance":1964},"ruiner":{"calculated":true,"class":"S+","performance":1446},"hunter":{"calculated":true,"class":"S","performance":808},"yosemite1500":{"calculated":true,"class":"S+","performance":1225},"avarus":{"calculated":true,"class":"S+","performance":1341},"z190":{"calculated":true,"class":"S","performance":819},"fixter":{"calculated":true,"class":"A","performance":704},"rookrb":{"calculated":true,"class":"D","performance":328},"f620":{"calculated":true,"class":"S+","performance":1413},"boxville5":{"calculated":true,"class":"D","performance":350},"nsandstorm":{"calculated":true,"class":"A","performance":789},"thraxs":{"performance":2347,"class":"S+","calculated":true},"inductor2":{"calculated":true,"class":"B","performance":498},"dubsta2":{"calculated":true,"class":"S+","performance":1137},"tulip":{"calculated":true,"class":"S","performance":884},"nightshade":{"calculated":true,"class":"A","performance":723},"postlude":{"calculated":true,"class":"B","performance":573},"btype":{"calculated":true,"class":"B","performance":600},"lguard":{"calculated":true,"class":"S","performance":830},"kurumata":{"performance":2267,"class":"S+","calculated":true},"seminole2":{"calculated":true,"class":"S+","performance":1137},"streamer216":{"calculated":true,"class":"S+","performance":1852},"dltenf2":{"calculated":true,"class":"S+","performance":2009},"gauntletstx":{"calculated":true,"class":"A","performance":723},"banshee":{"calculated":true,"class":"A","performance":755},"inductor":{"calculated":true,"class":"B","performance":498},"cutter":{"calculated":true,"class":"D","performance":328},"cruiser":{"calculated":true,"class":"B","performance":457},"bruiser":{"calculated":true,"class":"B","performance":438},"BearcatRBstairs":{"calculated":true,"class":"S+","performance":1137},"gauntlet":{"calculated":true,"class":"S","performance":852},"burrito4":{"calculated":true,"class":"S+","performance":1151},"coquette4":{"calculated":true,"class":"S","performance":918},"voltic2":{"calculated":true,"class":"S","performance":986},"kriegerc":{"calculated":true,"class":"S+","performance":2033},"guardian":{"calculated":true,"class":"S+","performance":1137},"dukes":{"calculated":true,"class":"A","performance":787},"issi2":{"calculated":true,"class":"S","performance":852},"asea":{"calculated":true,"class":"S","performance":986},"baller":{"calculated":true,"class":"S+","performance":1137},"vacca":{"calculated":true,"class":"S+","performance":1157},"tornado5":{"calculated":true,"class":"S+","performance":1173},"rebel2":{"calculated":true,"class":"S+","performance":1137},"freightcar2":{"calculated":true,"class":"S+","performance":6552},"osiris":{"calculated":true,"class":"S+","performance":1180},"alkonost":{"calculated":true,"class":"S+","performance":2291},"buffalo":{"calculated":true,"class":"S","performance":918},"stalion2":{"calculated":true,"class":"A","performance":787},"lurcher":{"calculated":true,"class":"S","performance":918},"flashgt":{"calculated":true,"class":"S","performance":999},"sabot":{"calculated":true,"class":"S","performance":951},"fcr2":{"calculated":true,"class":"S+","performance":1536},"rt3000":{"calculated":true,"class":"S","performance":884},"sandking":{"calculated":true,"class":"S+","performance":1137},"penetrator":{"calculated":true,"class":"S+","performance":1463},"stinger":{"calculated":true,"class":"S+","performance":1018},"monroe":{"calculated":true,"class":"S+","performance":1520},"polimpaler5":{"calculated":true,"class":"S+","performance":1195},"emsnspeedo":{"calculated":true,"class":"S+","performance":1564},"policeold2":{"calculated":true,"class":"S+","performance":1340},"md902aod":{"performance":896,"class":"S","calculated":true},"wolfsbane":{"calculated":true,"class":"S+","performance":1227},"dlcara":{"calculated":true,"class":"S+","performance":2335},"burrito5":{"calculated":true,"class":"S+","performance":1151},"comet3":{"calculated":true,"class":"S","performance":884},"dlturismo3":{"calculated":true,"class":"S+","performance":2797},"intruderc":{"calculated":true,"class":"S+","performance":4552},"vesper":{"calculated":true,"class":"S+","performance":1606},"entity2":{"calculated":true,"class":"S+","performance":1157},"surano3":{"calculated":true,"class":"S+","performance":1752},"bruiser3":{"calculated":true,"class":"B","performance":438},"koryprorcartel":{"performance":1774,"class":"S+","calculated":true},"towtruck4":{"calculated":true,"class":"S+","performance":1011},"elegy2":{"calculated":true,"class":"S+","performance":1159},"sentinel4":{"calculated":true,"class":"S","performance":951},"winky":{"calculated":true,"class":"A","performance":733},"pony":{"calculated":true,"class":"S+","performance":1151},"astron":{"calculated":true,"class":"S+","performance":1292},"voltic":{"calculated":true,"class":"S","performance":986},"fireeng":{"calculated":true,"class":"S+","performance":1542},"schwarzer":{"calculated":true,"class":"S+","performance":1018},"gauntlet2":{"calculated":true,"class":"S","performance":884},"rumpo":{"calculated":true,"class":"S+","performance":1151},"savestra":{"calculated":true,"class":"S+","performance":1018},"sabrecab":{"calculated":true,"class":"S+","performance":1225},"minivan":{"calculated":true,"class":"S+","performance":1409},"ratbike":{"calculated":true,"class":"S+","performance":1227},"issi8":{"calculated":true,"class":"S+","performance":1126},"virgo3":{"calculated":true,"class":"A","performance":617},"zr380":{"calculated":true,"class":"S","performance":884},"bison3":{"calculated":true,"class":"S+","performance":1072},"ratloader2":{"calculated":true,"class":"A","performance":661},"alphaz1":{"calculated":true,"class":"S+","performance":1318},"sheava":{"calculated":true,"class":"S","performance":884},"drifttampa":{"calculated":true,"class":"A","performance":732},"adder":{"calculated":true,"class":"S+","performance":1431},"thraxd":{"calculated":true,"class":"S+","performance":1279},"tractor2":{"calculated":true,"class":"D","performance":22},"duster":{"calculated":true,"class":"S+","performance":1932},"sheriff2":{"calculated":true,"class":"S+","performance":1137},"stingertt":{"calculated":true,"class":"S","performance":819},"jogger":{"calculated":true,"class":"S+","performance":1795},"rh82":{"performance":1957,"class":"S+","calculated":true},"comet6":{"calculated":true,"class":"S","performance":884},"mk21500dually":{"calculated":true,"class":"S+","performance":1431},"fbi":{"calculated":true,"class":"S","performance":918},"metrotrain":{"calculated":true,"class":"S+","performance":6552},"vamos":{"calculated":true,"class":"A","performance":693},"trailw":{"calculated":true,"class":"S+","performance":1502},"dune3":{"calculated":true,"class":"B","performance":600},"schafter6":{"calculated":true,"class":"S","performance":964},"bombushka":{"calculated":true,"class":"S+","performance":2237},"bansheepo":{"calculated":true,"class":"S+","performance":1660},"zr250":{"calculated":true,"class":"S+","performance":1733},"esskey":{"calculated":true,"class":"S+","performance":1536},"specter":{"calculated":true,"class":"S","performance":951},"issi5":{"calculated":true,"class":"B","performance":551},"sheriff":{"calculated":true,"class":"S","performance":986},"asbo":{"calculated":true,"class":"A","performance":632},"broadway":{"calculated":true,"class":"A","performance":765},"md902vagos":{"performance":896,"class":"S","calculated":true},"freightgrain":{"calculated":true,"class":"S+","performance":6552},"gstkrochavosv61":{"calculated":true,"class":"S","performance":986},"meteor":{"calculated":true,"class":"S+","performance":1157},"manchez2":{"calculated":true,"class":"S+","performance":1440},"youga":{"calculated":true,"class":"S+","performance":1080},"rumpo3":{"calculated":true,"class":"S+","performance":1137},"rhapsody":{"calculated":true,"class":"S","performance":852},"tornado6":{"calculated":true,"class":"B","performance":482},"gstyosemite1":{"calculated":true,"class":"S+","performance":1292},"sanchez2":{"calculated":true,"class":"S+","performance":1046},"pbus2":{"calculated":true,"class":"D","performance":247},"dlgranger":{"calculated":true,"class":"S+","performance":1678},"nightshark":{"calculated":true,"class":"A","performance":767},"schafter5":{"calculated":true,"class":"S+","performance":1124},"moonbeam":{"calculated":true,"class":"S+","performance":1080},"innovation":{"calculated":true,"class":"S+","performance":1305},"valkyrie":{"calculated":true,"class":"S","performance":830},"vorschlaghammer":{"calculated":true,"class":"S","performance":918},"everon":{"calculated":true,"class":"S","performance":825},"coquettewb":{"performance":1957,"class":"S+","calculated":true},"sdmonsterslayer":{"performance":2067,"class":"S+","calculated":true},"ruston":{"calculated":true,"class":"S","performance":857},"veto":{"calculated":true,"class":"B","performance":458},"coach":{"calculated":true,"class":"A","performance":767},"sm722":{"calculated":true,"class":"A","performance":755},"oracle":{"calculated":true,"class":"S","performance":986},"zeno":{"calculated":true,"class":"S","performance":988},"driftnebula":{"calculated":true,"class":"A","performance":684},"minivan2":{"calculated":true,"class":"S+","performance":1409},"greenwood":{"calculated":true,"class":"S+","performance":1318},"barracks2":{"calculated":true,"class":"C","performance":382},"polimpaler6":{"calculated":true,"class":"S","performance":830},"ingotc":{"calculated":true,"class":"S+","performance":1628},"yosemite2":{"calculated":true,"class":"B","performance":496},"viseris":{"calculated":true,"class":"S","performance":951},"riata":{"calculated":true,"class":"S","performance":967},"retinue2":{"calculated":true,"class":"S","performance":951},"taco":{"calculated":true,"class":"S","performance":808},"tractor":{"calculated":true,"class":"D","performance":44},"scharmann":{"calculated":true,"class":"S+","performance":1573},"dlcont":{"calculated":true,"class":"S+","performance":2379},"zion2":{"calculated":true,"class":"S+","performance":1564},"marshall":{"calculated":true,"class":"B","performance":442},"polcoach":{"calculated":true,"class":"S+","performance":1159},"patriot3":{"calculated":true,"class":"S","performance":884},"remustwo":{"calculated":true,"class":"S+","performance":1806},"bullet":{"calculated":true,"class":"S","performance":922},"slamvan3":{"calculated":true,"class":"A","performance":661},"dukes3":{"calculated":true,"class":"S","performance":819},"manana":{"calculated":true,"class":"S+","performance":1173},"banditojester":{"calculated":true,"class":"S+","performance":1228},"domc":{"calculated":true,"class":"S+","performance":1413},"prairie":{"calculated":true,"class":"S","performance":852},"castella":{"calculated":true,"class":"S","performance":964},"thruster":{"calculated":true,"class":"S+","performance":1044},"havok":{"calculated":true,"class":"S","performance":922},"btype2":{"calculated":true,"class":"B","performance":540},"brutus3":{"calculated":true,"class":"S+","performance":1008},"fbi2":{"calculated":true,"class":"S+","performance":1137},"baller8":{"calculated":true,"class":"S+","performance":1225},"nero":{"calculated":true,"class":"S+","performance":1361},"phantom2":{"calculated":true,"class":"B","performance":496},"blistacr":{"calculated":true,"class":"S","performance":884},"flatbed":{"calculated":true,"class":"S","performance":945},"biff":{"calculated":true,"class":"S+","performance":1618},"fq2":{"calculated":true,"class":"S+","performance":1551},"enduro":{"calculated":true,"class":"S+","performance":1101},"rsheli":{"calculated":true,"class":"S","performance":830},"buffalo2":{"calculated":true,"class":"S","performance":852},"rumpo2":{"calculated":true,"class":"S+","performance":1151},"envisage":{"calculated":true,"class":"S","performance":964},"monstrociti":{"calculated":true,"class":"S","performance":967},"elegy":{"calculated":true,"class":"S+","performance":1116},"dlswift":{"calculated":true,"class":"S","performance":830},"dominator8":{"calculated":true,"class":"S","performance":819},"nexus":{"calculated":true,"class":"S","performance":884},"chino":{"calculated":true,"class":"A","performance":639},"diablous":{"calculated":true,"class":"S+","performance":1498},"carbonizzare":{"calculated":true,"class":"S","performance":819},"infernus":{"calculated":true,"class":"S+","performance":1126},"clique3":{"calculated":true,"class":"S+","performance":1466},"dlkomoda":{"calculated":true,"class":"S+","performance":1939},"mule5":{"calculated":true,"class":"B","performance":438},"buccaneer2":{"calculated":true,"class":"S","performance":918},"washington":{"calculated":true,"class":"S+","performance":1340},"microlight":{"calculated":true,"class":"S+","performance":1596},"impaler2":{"calculated":true,"class":"A","performance":755},"dbvolante":{"calculated":true,"class":"S","performance":819},"citi":{"calculated":true,"class":"S","performance":852},"fusilade":{"calculated":true,"class":"S","performance":884},"schafter3":{"calculated":true,"class":"S+","performance":1157},"raptor":{"calculated":true,"class":"A","performance":788},"buffalo5":{"calculated":true,"class":"S+","performance":1062},"avenger3":{"calculated":true,"class":"S+","performance":1964},"sentinelmk4":{"calculated":true,"class":"S","performance":918},"omnis":{"calculated":true,"class":"S","performance":999},"zorrusso":{"calculated":true,"class":"S","performance":819},"bmx":{"calculated":true,"class":"S","performance":935},"terminus":{"calculated":true,"class":"S+","performance":1094},"stockade3":{"calculated":true,"class":"S+","performance":1830},"speedo2":{"calculated":true,"class":"S+","performance":1151},"verlierer2":{"calculated":true,"class":"S+","performance":1124},"dlbuffalo4":{"calculated":true,"class":"S+","performance":2625},"driftzr350":{"calculated":true,"class":"A","performance":684},"fagaloa":{"calculated":true,"class":"B","performance":482},"dilettante":{"calculated":true,"class":"A","performance":765},"patriot2":{"calculated":true,"class":"S+","performance":1137},"dlvigero2":{"calculated":true,"class":"S+","performance":2300},"velum2":{"calculated":true,"class":"S+","performance":2126},"oppressor":{"calculated":true,"class":"S+","performance":1729},"benson2":{"calculated":true,"class":"S+","performance":1480},"riot2":{"calculated":true,"class":"S+","performance":1011},"riot":{"calculated":true,"class":"S+","performance":1830},"cargobob2":{"calculated":true,"class":"S","performance":808},"r9gt":{"calculated":true,"class":"S","performance":819},"dlbuffalo":{"calculated":true,"class":"S+","performance":1596},"dlgranger2":{"calculated":true,"class":"S+","performance":2143},"technical3":{"calculated":true,"class":"S+","performance":1137},"volatol":{"calculated":true,"class":"S+","performance":1964},"jester5":{"calculated":true,"class":"S","performance":852},"habanero":{"calculated":true,"class":"S+","performance":1551},"coquette3":{"calculated":true,"class":"S","performance":819},"jester4wb":{"performance":2110,"class":"S+","calculated":true},"towtruck3":{"calculated":true,"class":"S+","performance":1011},"krieger":{"calculated":true,"class":"S+","performance":1311},"streiter2":{"calculated":true,"class":"S","performance":847},"serrano":{"calculated":true,"class":"S+","performance":1270},"handler":{"calculated":true,"class":"D","performance":22},"savage":{"calculated":true,"class":"A","performance":765},"komoda":{"calculated":true,"class":"S","performance":819},"brioso3":{"calculated":true,"class":"A","performance":670},"stockade":{"calculated":true,"class":"S+","performance":1830},"towtruck2":{"calculated":true,"class":"S","performance":808},"dljugular":{"calculated":true,"class":"S+","performance":2258},"kuruma2":{"calculated":true,"class":"S+","performance":1008},"avenger4":{"calculated":true,"class":"S+","performance":1964},"vigilante":{"calculated":true,"class":"S","performance":830},"cuban800":{"calculated":true,"class":"S+","performance":2208},"adders":{"calculated":true,"class":"S+","performance":1431},"frogger":{"calculated":true,"class":"S","performance":830},"freight2":{"calculated":true,"class":"S+","performance":6552},"fcomneisgt25":{"performance":1772,"class":"S+","calculated":true},"blista3":{"calculated":true,"class":"S","performance":884},"buffalo3":{"calculated":true,"class":"S","performance":884},"streiter":{"calculated":true,"class":"S+","performance":1502},"police2":{"calculated":true,"class":"S","performance":918},"niobe":{"calculated":true,"class":"S+","performance":1126},"dlvstr":{"calculated":true,"class":"S+","performance":2450},"surfer":{"calculated":true,"class":"D","performance":276},"asterope":{"calculated":true,"class":"S","performance":986},"rallytruck":{"calculated":true,"class":"A","performance":656},"arias":{"calculated":true,"class":"S+","performance":1267},"paradise":{"calculated":true,"class":"S+","performance":1151},"gburrito":{"calculated":true,"class":"S+","performance":1151},"turismoo":{"calculated":true,"class":"S+","performance":1157},"dlrhine":{"calculated":true,"class":"S+","performance":2218},"camper":{"calculated":true,"class":"S","performance":808},"feltzer2":{"calculated":true,"class":"S","performance":884},"rentalbus":{"calculated":true,"class":"B","performance":496},"polmav":{"calculated":true,"class":"S","performance":830},"minitank":{"calculated":true,"class":"B","performance":404},"turismo3":{"calculated":true,"class":"A","performance":755},"coquettec5c":{"calculated":true,"class":"S+","performance":7934},"ambulance":{"calculated":true,"class":"S+","performance":1624},"lentus":{"calculated":true,"class":"S+","performance":1225},"asterope2":{"calculated":true,"class":"S","performance":986},"airbus":{"calculated":true,"class":"A","performance":767},"stryder":{"calculated":true,"class":"A","performance":711},"nimbus":{"calculated":true,"class":"S+","performance":2923},"impaler":{"calculated":true,"class":"A","performance":733},"impaler6":{"calculated":true,"class":"S","performance":830},"retinue":{"calculated":true,"class":"S+","performance":1018},"sanctus":{"calculated":true,"class":"S+","performance":1348},"zrgpr":{"calculated":true,"class":"S+","performance":1283},"cheetahfel":{"calculated":true,"class":"S+","performance":1907},"sultanrs":{"calculated":true,"class":"S+","performance":1191},"weevilup":{"calculated":true,"class":"S+","performance":1502},"rebla":{"calculated":true,"class":"S+","performance":1030},"nemesis":{"calculated":true,"class":"S+","performance":1337},"neo":{"calculated":true,"class":"S+","performance":1126},"primo":{"calculated":true,"class":"S","performance":918},"deluxo":{"calculated":true,"class":"S","performance":986},"tachyon":{"calculated":true,"class":"S","performance":884},"brickade":{"calculated":true,"class":"A","performance":656},"cavalcade2":{"calculated":true,"class":"S+","performance":1072},"dump":{"calculated":true,"class":"D","performance":0},"dominator4":{"calculated":true,"class":"A","performance":693},"seasparrow3":{"calculated":true,"class":"S","performance":922},"specter2":{"calculated":true,"class":"S","performance":884},"seabreeze":{"calculated":true,"class":"S+","performance":17780},"verus":{"calculated":true,"class":"A","performance":789},"furiawb":{"performance":1957,"class":"S+","calculated":true},"dominator9":{"calculated":true,"class":"S","performance":852},"hauler2":{"calculated":true,"class":"B","performance":438},"bestiagts":{"calculated":true,"class":"S+","performance":1159},"autarch":{"calculated":true,"class":"S","performance":819},"cogcabrio":{"calculated":true,"class":"S","performance":986},"regina":{"calculated":true,"class":"A","performance":765},"dloutlaw":{"calculated":true,"class":"S+","performance":1859},"monster":{"calculated":true,"class":"B","performance":442},"deathbike2":{"calculated":true,"class":"S+","performance":2228},"yosemite3":{"calculated":true,"class":"S","performance":906},"superd":{"calculated":true,"class":"S","performance":964},"supergts":{"calculated":true,"class":"S+","performance":1881}}